{
  "collectionName": "components_section_lascana_sections",
  "info": {
    "displayName": "Lascana Section",
    "icon": "collapse"
  },
  "options": {},
  "attributes": {
    "lascanaIcon": {
      "allowedTypes": [
        "images",
        "files",
        "videos",
        "audios"
      ],
      "type": "media",
      "multiple": false
    },
    "title": {
      "type": "string"
    },
    "description": {
      "type": "text"
    },
    "button": {
      "displayName": "Button",
      "type": "component",
      "repeatable": true,
      "component": "element.button"
    },
    "gallery": {
      "displayName": "Gallery",
      "type": "component",
      "repeatable": true,
      "component": "element.gallery"
    }
  }
}
